twitterframe/__init__.py
twitterframe/main.py
twitterframe/scripts/__init__.py
twitterframe/scripts/twitter_listener.py
twitterframe/scripts/twitter_methods.py
twitterframe/scripts/utils.py
twitterframe-1.0.0.dist-info/LICENSE.md
twitterframe-1.0.0.dist-info/METADATA
twitterframe-1.0.0.dist-info/WHEEL
twitterframe-1.0.0.dist-info/entry_points.txt
twitterframe-1.0.0.dist-info/top_level.txt
twitterframe-1.0.0.dist-info/RECORD
