Metadata-Version: 2.1
Name: twitterframe
Version: 1.0.0
Summary: A basic command line application used in tandem with Twitter API to frame anything from Twitter into a Pandas DataFrame, or exported as a CSV.
Home-page: https://github.com/Ruwai/twitterframe
Author: Ruwai
License: UNKNOWN
Platform: UNKNOWN
Classifier: Programming Language :: Python :: 3
Classifier: License :: OSI Approved :: GNU General Public License v3 (GPLv3)
Classifier: Operating System :: OS Independent
Classifier: Development Status :: 4 - Beta
Requires-Python: >=3.5
Requires-Dist: tweepy
Requires-Dist: pandas
Requires-Dist: click
